LICENSE.txt
MANIFEST.in
README.md
pyproject.toml
setup.cfg
setup.py
dj_ninja_auth/__init__.py
dj_ninja_auth/app_settings.py
dj_ninja_auth/apps.py
dj_ninja_auth/controller.py
dj_ninja_auth/forms.py
dj_ninja_auth/schema.py
dj_ninja_auth/schema_control.py
dj_ninja_auth.egg-info/PKG-INFO
dj_ninja_auth.egg-info/SOURCES.txt
dj_ninja_auth.egg-info/dependency_links.txt
dj_ninja_auth.egg-info/requires.txt
dj_ninja_auth.egg-info/top_level.txt
dj_ninja_auth/authtoken/__init__.py
dj_ninja_auth/authtoken/admin.py
dj_ninja_auth/authtoken/app_settings.py
dj_ninja_auth/authtoken/apps.py
dj_ninja_auth/authtoken/authentication.py
dj_ninja_auth/authtoken/controller.py
dj_ninja_auth/authtoken/models.py
dj_ninja_auth/authtoken/schema.py
dj_ninja_auth/authtoken/schema_control.py
dj_ninja_auth/authtoken/migrations/0001_initial.py
dj_ninja_auth/authtoken/migrations/__init__.py
dj_ninja_auth/jwt/__init__.py
dj_ninja_auth/jwt/app_settings.py
dj_ninja_auth/jwt/apps.py
dj_ninja_auth/jwt/authentication.py
dj_ninja_auth/jwt/backends.py
dj_ninja_auth/jwt/controller.py
dj_ninja_auth/jwt/exceptions.py
dj_ninja_auth/jwt/schema.py
dj_ninja_auth/jwt/schema_control.py
dj_ninja_auth/jwt/state.py
dj_ninja_auth/jwt/tokens.py
dj_ninja_auth/jwt/utils.py
dj_ninja_auth/registration/__init__.py
dj_ninja_auth/registration/adapter.py
dj_ninja_auth/registration/app_settings.py
dj_ninja_auth/registration/apps.py
dj_ninja_auth/registration/controller.py
dj_ninja_auth/registration/schema.py
dj_ninja_auth/registration/schema_control.py
dj_ninja_auth/templates/password/reset_email.html