Metadata-Version: 2.1
Name: dj-ninja-auth
Version: 0.1.10
Summary: A Django app for REST Authentication using Django Ninja
Home-page: https://github.com/majulahsingapuri/dj-ninja-auth
Author: Bhargav Singapuri
Author-email: bhsingapuri@gmail.com
License: MIT
Project-URL: Documentation, https://bhargav.io/ninja-auth
Classifier: Environment :: Web Environment
Classifier: Framework :: Django
Classifier: Framework :: Django :: 4.2
Classifier: Intended Audience :: Developers
Classifier: License :: OSI Approved :: BSD License
Classifier: Operating System :: OS Independent
Classifier: Programming Language :: Python
Classifier: Programming Language :: Python :: 3
Classifier: Programming Language :: Python :: 3 :: Only
Classifier: Programming Language :: Python :: 3.8
Classifier: Programming Language :: Python :: 3.9
Classifier: Programming Language :: Python :: 3.10
Classifier: Programming Language :: Python :: 3.11
Classifier: Programming Language :: Python :: 3.12
Classifier: Topic :: Internet :: WWW/HTTP
Classifier: Topic :: Internet :: WWW/HTTP :: Dynamic Content
Requires-Python: >=3.10
Provides-Extra: allauth
License-File: LICENSE.txt
